{"info":{"partnerName":"Alessi","name":"SG74 Babà, stool/laundry basket with lid","price":"545.0","productURL":"http://store.alessi.com/cwss/Cart/add?ean=8003299912964","height":"465","width":"360","depth":"360","partnerId":"BTsd","images":{"full":["a/503htUII5suiUw9BbxqvtT1t4dM.jpg"],"brand":"a/4kJGRDIpwCi1EEgjNmPsgaAJxog.png","thumb":["a/3b7967111ad07e38b865cad78205a9351a515e08.jpg"]},"customerId":"SG74","description":"Sgabello/porta biancheria con seduta in acciaio inossidabile 18/10 lucido e legno.<br><br>Stool/laundry basket with lid in 18/10 stainless steel mirror polished and wood."},"status":"ENABLED","id":"ne2U"}