{"info":{"partnerName":"Confident Living","name":"Pedrera ABC bordslampa","price":"1 995,00 kr","productURL":"http://confidentliving.se/produkt/pedrera-abc-bordslampa/25571142","height":"35.0 cm","width":"18.0 cm","depth":"18.0 cm","partnerId":"XGTP","images":{"brand":"a/_WM9plvAwdAkIpvyaDR1bUjwJh4.png","full":["a/7bj-T3GXSJFcqJ5aOCwNTBS0J4s.jpg"],"thumb":["a/26rHqK8aZy8aQ-tAimyb--3x2TE.jpg"]},"customerId":"25571142","description":"Pedreralampan skapades 1955 och är döpt efter Gaudis byggnad i Barcelona med samma namn. Det var när vindsförråden i Pedrerahuset skulle göras om till tretton lägenheter (numrerade 1 – 14 för att inte väcka anstöt hos skrockfulla hyresgäster) som arkitekt Barba Corsini skapade denna serie lampor. De runda fönstren och mjuka linjerna i Gaudis originalform går tydligt igen i Pedrera!"},"status":"ENABLED","id":"zssw","order":"R"}