{"info":{"partnerName":"Alessi","name":"FM22 B - ALDO, flower vase","price":"254.0","productURL":"http://store.alessi.com/cwss/Cart/add?ean=8003299335671","height":"255","width":"260","depth":"160","partnerId":"BTsd","images":{"full":["a/rZnMdKzXzCRk_BuvN8CRIP0c1sM.jpg"],"brand":"a/4kJGRDIpwCi1EEgjNmPsgaAJxog.png","thumb":["a/796ed65fb0fbd18cca4478f5c5e6fe37723ceda9.jpg"]},"customerId":"FM22","description":"vaso per fiori in porcellana, bianco. Interno arancio.<br><br>flower vase in porcelain, white. Orange inside."},"status":"ENABLED","id":"BJft"}