{"status":"ENABLED","info":{"partnerName":"Sits","name":"Colorado","tags":[""],"depth":"205 cm","height":"81 cm","width":"355 cm","productURL":"http://www.sits.eu/en/home/furniture-collection/tea-and-book/item/colorado","partnerId":"Trl6","images":{"brand":"a/Mt-FasOltv-DqzKcvEzWlbJ9M5E.png","full":["a/jWZ-7Nuxud5Pkhx2jpXj7BcoYIM.jpg"],"thumb":["a/f8a6be300582a35fdc323eac38feeb9f86ecc4b5.jpg"]},"customerId":"COLORADO","description":"COLORADO will let you appreciate the benefits of a large family. COLORADO is big, comfortable and modern, and the units in this collection are designed to seat many people. With the large seats and many cushions, COLORADO will give all your family maximum comfort during family celebrations. The COLORADO family is also impressive – it includes armchairs, sofas and corner sofas available in various sizes and arrangements. COLORADO – family celebrations every day."},"id":"ccwV"}