{"info":{"partnerName":"Alessi","name":"FC15 - Blow up, magazine holder","price":"133.0","productURL":"http://store.alessi.com/cwss/Cart/add?ean=8003299935116","height":"350","width":"455","depth":"285","partnerId":"BTsd","images":{"full":["a/6LPEpq3Xk2aEkiqASv_HqJgVVsI.jpg"],"brand":"a/4kJGRDIpwCi1EEgjNmPsgaAJxog.png","thumb":["a/b7cd2700dcaebb473b6484a7162207357bd82f06.jpg"]},"customerId":"FC15","description":"portariviste in acciaio cromato.<br><br>magazine holder in steel chrome-plated."},"status":"ENABLED","id":"DVH8"}