{"info":{"partnerName":"Serralunga","name":"Canisse Sofa","price":"1890.0","productURL":"http://www.serralunga.com/product.htm?lang=en&prod=Canisse%20Divano","height":"80","width":"173","depth":"88","partnerId":"UvGm","images":{"brand":"a/fAMMHHdzlIN9Anckbl2sDxJ2Bs8.png","full":["a/Dg-P-d0C8l9Widdj1_oGqfesx7c.jpg"],"thumb":["a/XjrImtRTvFfoOZ7uuSiIKrWjv-Y.jpg"]},"customerId":"CANISSE-SO","description":"Together with French designer Philippe Nigro, Serralunga has developed Canisse; an outdoor chair with an extremely natural look. Canisse is an open-air shelter, a protected place with large cushions inside to invite relaxation. "},"status":"ENABLED","id":"wbKf","order":"135"}